{
  "type": "Feature",
  "properties": {
    "gn:country":"GL",
    "gn:fcode":"ADM3",
    "gn:population":3330,
    "iso:country":"GL",
    "name:dan_x_preferred":[
        "Aasiaat Kommune"
    ],
    "name:und_x_variant":[
        "Aasiaat"
    ],
    "qs_pg:aaroncc":"GL",
    "qs_pg:gn_country":"GL",
    "qs_pg:gn_fcode":"ADM3",
    "qs_pg:gn_pop":3330,
    "qs_pg:name":"Aasiaat Kommuniat",
    "qs_pg:photos_9r":0,
    "qs_pg:photos_sr":0,
    "qs_pg:pop_sr":4,
    "qs_pg:qs_pg_placetype":"localadmin",
    "wof:name":"Aasiaat Kommuniat",
    "wof:placetype":"localadmin",
    "wof:population":3330
},
  "geometry": {"coordinates":[-52.75,68.66667],"type":"Point"}
}