{
  "type": "Feature",
  "properties": {
    "gn:population":195,
    "iso:country":"GL",
    "name:cze_x_preferred":[
        "Ukkusissat"
    ],
    "name:dan_x_preferred":[
        "Ukkusissat"
    ],
    "name:dut_x_preferred":[
        "Ukkusissat"
    ],
    "name:eng_x_preferred":[
        "Ukkusissat"
    ],
    "name:fra_x_preferred":[
        "Ukkusissat"
    ],
    "name:fre_x_preferred":[
        "Ukkusissat"
    ],
    "name:geo_x_preferred":[
        "\u10e3\u10d9\u10e3\u10e1\u10d8\u10e1\u10d0\u10e2\u10d8"
    ],
    "name:ger_x_preferred":[
        "Ukkusissat"
    ],
    "name:ita_x_preferred":[
        "Ukkusissat"
    ],
    "name:kal_x_preferred":[
        "Ukkusissat"
    ],
    "name:kat_x_preferred":[
        "\u10e3\u10d9\u10e3\u10e1\u10d8\u10e1\u10d0\u10e2\u10d8"
    ],
    "name:nld_x_preferred":[
        "Ukkusissat"
    ],
    "name:nob_x_preferred":[
        "Ukkusissat"
    ],
    "name:nor_x_preferred":[
        "Ukkusissat"
    ],
    "name:pol_x_preferred":[
        "Ukkusissat"
    ],
    "name:por_x_preferred":[
        "Ukkusissat"
    ],
    "name:rus_x_preferred":[
        "\u0423\u043a\u043a\u0443\u0441\u0438\u0441\u0441\u0430\u0442"
    ],
    "name:spa_x_preferred":[
        "Ukkusissat"
    ],
    "name:swe_x_preferred":[
        "Ukkusissat"
    ],
    "name:unk_x_variant":[
        "Uvkusigssat"
    ],
    "qs:a0":"Kalaallit Nunaat#Gr\u00f8nland",
    "qs:a1":"*Qaasuitsup Kommunia",
    "qs:a1r":"0",
    "qs:adm0":"Kalaallit Nunaat#Gr\u00f8nland",
    "qs:la_lc":"*",
    "qs:level":"locality",
    "qs:loc":"Ukkusissat",
    "qs:loc_alt":"Ukkusissat",
    "qs:pop":0,
    "qs:type":"buffered point",
    "wd:wordcount":461,
    "wof:name":"Ukkusissat",
    "wof:placetype":"locality",
    "wof:population":195
},
  "geometry": {"coordinates":[-51.900001,71.050003],"type":"Point"}
}