{
  "type": "Feature",
  "properties": {
    "gn:admin1_code":"05",
    "gn:asciiname":"Nuugaaq",
    "gn:country_code":"GL",
    "gn:dem":1,
    "gn:feature_class":"P",
    "gn:feature_code":"PPL",
    "gn:name":"Nuugaaq",
    "gn:population":0,
    "gn:timezone":"America/Godthab",
    "iso:country":"GL",
    "name:und_x_variant":[
        "N\u00fbg\u00e2q",
        "Nugak",
        "Nuugaaq"
    ],
    "wof:name":"Nuugaaq",
    "wof:placetype":"locality"
},
  "geometry": {"coordinates":[-51.26667,69.96666999999999],"type":"Point"}
}