{
  "type": "Feature",
  "properties": {
    "gn:population":18,
    "iso:country":"GL",
    "name:ara_x_preferred":[
        "\u0643\u064a\u0643\u064a\u0631\u062a\u0627\u062a"
    ],
    "name:cat_x_preferred":[
        "Qeqertat"
    ],
    "name:ces_x_preferred":[
        "Qeqertat"
    ],
    "name:dan_x_preferred":[
        "Qeqertat"
    ],
    "name:deu_x_preferred":[
        "Qeqertat"
    ],
    "name:eng_x_preferred":[
        "Qeqertat"
    ],
    "name:fra_x_preferred":[
        "Qeqertat"
    ],
    "name:ita_x_preferred":[
        "Qeqertat"
    ],
    "name:kat_x_preferred":[
        "\u10d9\u10d4\u10d9\u10d4\u10e0\u10e2\u10d0\u10e2\u10d8"
    ],
    "name:nld_x_preferred":[
        "Qeqertat"
    ],
    "name:nob_x_preferred":[
        "Qeqertat"
    ],
    "name:pol_x_preferred":[
        "Qeqertat"
    ],
    "name:por_x_preferred":[
        "Qeqertat"
    ],
    "name:rus_x_preferred":[
        "\u041a\u0435\u043a\u0435\u0440\u0442\u0430\u0442"
    ],
    "name:spa_x_preferred":[
        "Qeqertat"
    ],
    "name:swe_x_preferred":[
        "Qeqertat"
    ],
    "name:unk_x_variant":[
        "Kekertat"
    ],
    "qs:a0":"Kalaallit Nunaat#Gr\u00f8nland",
    "qs:a1":"*Qaasuitsup Kommunia",
    "qs:a1r":"0",
    "qs:adm0":"Kalaallit Nunaat#Gr\u00f8nland",
    "qs:la_lc":"*",
    "qs:level":"locality",
    "qs:loc":"Qeqertat",
    "qs:loc_alt":"Qeqertat",
    "qs:pop":0,
    "qs:type":"buffered point",
    "wd:wordcount":81,
    "wof:name":"Qeqertat",
    "wof:placetype":"locality",
    "wof:population":18
},
  "geometry": {"coordinates":[-66.69461099999999,77.49851200000001],"type":"Point"}
}