{
  "type": "Feature",
  "properties": {
    "gn:country":"GL",
    "iso:country":"GL",
    "qs_pg:aaroncc":"GL",
    "qs_pg:gn_country":"GL",
    "qs_pg:name":"Holsteinsborg",
    "qs_pg:name_adm0":"Gr\u00f8nland",
    "qs_pg:name_adm1":"Vestgronland",
    "qs_pg:photos":150,
    "qs_pg:photos_1k":30,
    "qs_pg:photos_9k":1,
    "qs_pg:photos_9r":3,
    "qs_pg:photos_all":150,
    "qs_pg:photos_sr":3,
    "qs_pg:pop_sr":0,
    "qs_pg:qs_pg_placetype":"locality",
    "qs_pg:qs_pg_placetype_gp":"Town",
    "qs_pg:woe_adm0":23424828,
    "woe:adm0_id":23424828,
    "woe:name_adm0":"Gr\u00f8nland",
    "woe:name_adm1":"Vestgronland",
    "woe:placetype":"Town",
    "wof:name":"Holsteinsborg",
    "wof:placetype":"locality"
},
  "geometry": {"coordinates":[-53.66538,66.939273],"type":"Point"}
}