{
  "type": "Feature",
  "properties": {
    "gn:population":110,
    "iso:country":"GL",
    "name:ara_x_preferred":[
        "\u0633\u0627\u0631\u0641\u0627\u0646\u062c\u0648\u064a\u062a"
    ],
    "name:ast_x_preferred":[
        "Sarfannguit"
    ],
    "name:cat_x_preferred":[
        "Sarfannguit"
    ],
    "name:ceb_x_preferred":[
        "Sarfannguaq"
    ],
    "name:ces_x_preferred":[
        "Sarfannguit"
    ],
    "name:dan_x_preferred":[
        "Sarfannguit"
    ],
    "name:deu_x_preferred":[
        "Sarfannguit"
    ],
    "name:eng_x_preferred":[
        "Sarfannguit"
    ],
    "name:fra_x_preferred":[
        "Sarfannguit"
    ],
    "name:ita_x_preferred":[
        "Sarfannguaq"
    ],
    "name:jpn_x_preferred":[
        "\u30b5\u30eb\u30d5\u30a1\u30f3\u30b0\u30a2\u30af"
    ],
    "name:kal_x_preferred":[
        "Sarfannguaq"
    ],
    "name:kat_x_preferred":[
        "\u10e1\u10d0\u10e0\u10e4\u10d0\u10dc\u10d2\u10e3\u10d8\u10e2\u10d8"
    ],
    "name:nld_x_preferred":[
        "Sarfannguit"
    ],
    "name:nob_x_preferred":[
        "Sarfannguaq"
    ],
    "name:nor_x_preferred":[
        "Sarfannguaq"
    ],
    "name:pol_x_preferred":[
        "Sarfannguit"
    ],
    "name:por_x_preferred":[
        "Sarfannguit"
    ],
    "name:rus_x_preferred":[
        "\u0421\u0430\u0440\u0444\u0430\u043d\u043d\u0433\u0443\u0430\u043a"
    ],
    "name:spa_x_preferred":[
        "Sarfannguit"
    ],
    "name:swe_x_preferred":[
        "Sarfannguit"
    ],
    "name:swe_x_variant":[
        "Sarfannguaq"
    ],
    "name:und_x_variant":[
        "Sarfanguak"
    ],
    "qs:a0":"Kalaallit Nunaat#Gr\u00f8nland",
    "qs:a1":"*Qeqqata Kommunia",
    "qs:a1r":"0",
    "qs:adm0":"Kalaallit Nunaat#Gr\u00f8nland",
    "qs:la_lc":"*",
    "qs:level":"locality",
    "qs:loc":"Sarfannguit",
    "qs:loc_alt":"Sarfannguit",
    "qs:pop":0,
    "qs:type":"buffered point",
    "wd:wordcount":314,
    "wof:name":"Sarfannguit",
    "wof:placetype":"locality",
    "wof:population":110
},
  "geometry": {"coordinates":[-52.858333,66.90405],"type":"Point"}
}