{
  "type": "Feature",
  "properties": {
    "gn:population":336,
    "iso:country":"GL",
    "name:cze_x_preferred":[
        "Niaqornaarsuk"
    ],
    "name:dan_x_preferred":[
        "Niaqornaarsuk"
    ],
    "name:deu_x_preferred":[
        "Niaqornaarsuk"
    ],
    "name:dut_x_preferred":[
        "Niaqornaarsuk"
    ],
    "name:eng_x_preferred":[
        "Niaqornaarsuk"
    ],
    "name:fra_x_preferred":[
        "Niaqornaarsuk"
    ],
    "name:fre_x_preferred":[
        "Niaqornaarsuk"
    ],
    "name:geo_x_preferred":[
        "\u10dc\u10d8\u10d0\u10d9\u10dd\u10e0\u10dc\u10d0\u10d0\u10e0\u10e1\u10e3\u10d9\u10d8"
    ],
    "name:ger_x_preferred":[
        "Niaqornaarsuk"
    ],
    "name:ita_x_preferred":[
        "Niaqornaarsuk"
    ],
    "name:kal_x_preferred":[
        "Niaqornaarsuk"
    ],
    "name:kat_x_preferred":[
        "\u10dc\u10d8\u10d0\u10d9\u10dd\u10e0\u10dc\u10d0\u10d0\u10e0\u10e1\u10e3\u10d9\u10d8"
    ],
    "name:nld_x_preferred":[
        "Niaqornaarsuk"
    ],
    "name:nob_x_preferred":[
        "Niaqornaarsuk"
    ],
    "name:nor_x_preferred":[
        "Niaqornaarsuk"
    ],
    "name:pol_x_preferred":[
        "Niaqornaarsuk"
    ],
    "name:por_x_preferred":[
        "Niaqornaarsuk"
    ],
    "name:rus_x_preferred":[
        "\u041d\u0438\u0430\u043a\u043e\u0440\u043d\u0430\u0430\u0440\u0441\u0443\u043a"
    ],
    "name:spa_x_preferred":[
        "Niaqornaarsuk"
    ],
    "name:swe_x_preferred":[
        "Niaqornaarsuk"
    ],
    "name:unk_x_variant":[
        "Niakornarsuk"
    ],
    "qs:a0":"Kalaallit Nunaat#Gr\u00f8nland",
    "qs:a1":"*Qaasuitsup Kommunia",
    "qs:a1r":"0",
    "qs:adm0":"Kalaallit Nunaat#Gr\u00f8nland",
    "qs:la_lc":"*",
    "qs:level":"locality",
    "qs:loc":"Niaqornaarsuk",
    "qs:loc_alt":"Niaqornaarsuk",
    "qs:pop":0,
    "qs:type":"buffered point",
    "wd:wordcount":130,
    "wof:name":"Niaqornaarsuk",
    "wof:placetype":"locality",
    "wof:population":336
},
  "geometry": {"coordinates":[-52.853641,68.24236000000001],"type":"Point"}
}