{
  "type": "Feature",
  "properties": {
    "gn:admin1_code":"05",
    "gn:asciiname":"Killiat",
    "gn:country_code":"GL",
    "gn:dem":-9999,
    "gn:feature_class":"P",
    "gn:feature_code":"PPL",
    "gn:name":"Killiat",
    "gn:population":0,
    "gn:timezone":"America/Godthab",
    "iso:country":"GL",
    "name:und_x_variant":[
        "Kitdliat",
        "Killiat"
    ],
    "wof:name":"Killiat",
    "wof:placetype":"locality"
},
  "geometry": {"coordinates":[-53.78333000000001,68.28333000000001],"type":"Point"}
}