{
  "type": "Feature",
  "properties": {
    "gn:population":145,
    "iso:country":"GL",
    "name:ara_x_preferred":[
        "\u0622\u0631\u0633\u0648\u0643"
    ],
    "name:bul_x_preferred":[
        "\u0410\u0440\u0441\u0443\u043a"
    ],
    "name:cat_x_preferred":[
        "Arsuk"
    ],
    "name:ceb_x_preferred":[
        "Arsuk"
    ],
    "name:ces_x_preferred":[
        "Arsuk"
    ],
    "name:dan_x_preferred":[
        "Arsuk"
    ],
    "name:deu_x_preferred":[
        "Arsuk"
    ],
    "name:eng_x_preferred":[
        "Arsuk"
    ],
    "name:eus_x_preferred":[
        "Arsuk"
    ],
    "name:fin_x_preferred":[
        "Arsuk"
    ],
    "name:fra_x_preferred":[
        "Arsuk"
    ],
    "name:hye_x_preferred":[
        "\u0531\u0580\u057d\u0578\u0582\u056f"
    ],
    "name:ita_x_preferred":[
        "Arsuk"
    ],
    "name:kal_x_preferred":[
        "Arsuk"
    ],
    "name:kat_x_preferred":[
        "\u10d0\u10e0\u10e1\u10e3\u10d9\u10d8"
    ],
    "name:nld_x_preferred":[
        "Arsuk"
    ],
    "name:nob_x_preferred":[
        "Arsuk"
    ],
    "name:nor_x_preferred":[
        "Arsuk"
    ],
    "name:pol_x_preferred":[
        "Arsuk"
    ],
    "name:por_x_preferred":[
        "Arsuk"
    ],
    "name:rus_x_preferred":[
        "\u0410\u0440\u0441\u0443\u043a"
    ],
    "name:spa_x_preferred":[
        "Arsuk"
    ],
    "name:swe_x_preferred":[
        "Arsuk"
    ],
    "qs:a0":"Kalaallit Nunaat#Gr\u00f8nland",
    "qs:a1":"*Kommuneqarfik Sermersooq",
    "qs:a1r":"0",
    "qs:adm0":"Kalaallit Nunaat#Gr\u00f8nland",
    "qs:la_lc":"*",
    "qs:level":"locality",
    "qs:loc":"Arsuk",
    "qs:loc_alt":"Arsuk",
    "qs:pop":0,
    "qs:type":"buffered point",
    "wd:wordcount":436,
    "wof:name":"Arsuk",
    "wof:placetype":"locality",
    "wof:population":145
},
  "geometry": {"coordinates":[-48.453434,61.206585],"type":"Point"}
}