{
  "type": "Feature",
  "properties": {
    "iso:country":"GL",
    "name:ara_x_preferred":[
        "\u0643\u064a\u062a\u0633\u064a\u0633\u0648\u0627\u0631\u0633\u0648\u064a\u062a"
    ],
    "name:cze_x_preferred":[
        "Kitsissuarsuit"
    ],
    "name:dan_x_preferred":[
        "Kitsissuarsuit"
    ],
    "name:dut_x_preferred":[
        "Kitsissuarsuit"
    ],
    "name:eng_x_preferred":[
        "Kitsissuarsuit"
    ],
    "name:est_x_preferred":[
        "Kitsissuarsuit"
    ],
    "name:fra_x_preferred":[
        "Kitsissuarsuit"
    ],
    "name:fre_x_preferred":[
        "Kitsissuarsuit"
    ],
    "name:geo_x_preferred":[
        "\u10d9\u10d8\u10e2\u10e1\u10d8\u10e1\u10e3\u10d0\u10e0\u10e1\u10e3\u10d8\u10e2\u10d8"
    ],
    "name:ger_x_preferred":[
        "Kitsissuarsuit"
    ],
    "name:ita_x_preferred":[
        "Kitsissuarsuit"
    ],
    "name:kat_x_preferred":[
        "\u10d9\u10d8\u10e2\u10e1\u10d8\u10e1\u10e3\u10d0\u10e0\u10e1\u10e3\u10d8\u10e2\u10d8"
    ],
    "name:nob_x_preferred":[
        "Kitsissuarsuit"
    ],
    "name:nor_x_preferred":[
        "Kitsissuarsuit"
    ],
    "name:pol_x_preferred":[
        "Kitsissuarsuit"
    ],
    "name:por_x_preferred":[
        "Kitsissuarsuit"
    ],
    "name:rus_x_preferred":[
        "\u041a\u0438\u0442\u0441\u0438\u0441\u0441\u0443\u0430\u0440\u0441\u0443\u0438\u0442"
    ],
    "name:spa_x_preferred":[
        "Kitsissuarsuit"
    ],
    "name:swe_x_preferred":[
        "Kitsissuarsuit"
    ],
    "qs:a0":"Kalaallit Nunaat#Gr\u00f8nland",
    "qs:a1":"*Qaasuitsup Kommunia",
    "qs:a1r":"0",
    "qs:adm0":"Kalaallit Nunaat#Gr\u00f8nland",
    "qs:la_lc":"*",
    "qs:level":"locality",
    "qs:loc":"Kitsissuarsuit",
    "qs:loc_alt":"Kitsissuarsuit",
    "qs:pop":0,
    "qs:type":"buffered point",
    "wd:wordcount":241,
    "wof:name":"Kitsissuarsuit",
    "wof:placetype":"locality"
},
  "geometry": {"coordinates":[-53.112651,68.862407],"type":"Point"}
}