{
  "type": "Feature",
  "properties": {
    "gn:admin1_code":"07",
    "gn:asciiname":"Kangeq",
    "gn:country_code":"GL",
    "gn:dem":-9999,
    "gn:feature_class":"P",
    "gn:feature_code":"PPL",
    "gn:name":"Kangeq",
    "gn:population":0,
    "gn:timezone":"America/Godthab",
    "iso:country":"GL",
    "name:und_x_variant":[
        "Kangek",
        "Kangeq"
    ],
    "wof:name":"Kangeq",
    "wof:placetype":"locality"
},
  "geometry": {"coordinates":[-52.05,64.11667],"type":"Point"}
}