{
  "type": "Feature",
  "properties": {
    "gn:country":"GL",
    "gn:fcode":"PPL",
    "gn:population":154,
    "iso:country":"GL",
    "name:ara_x_preferred":[
        "\u0646\u0627\u0631\u0633\u0627\u0631\u0633\u0648\u0627\u0643"
    ],
    "name:cat_x_preferred":[
        "Narsarsuaq"
    ],
    "name:ceb_x_preferred":[
        "Narsarsuaq"
    ],
    "name:ces_x_preferred":[
        "Narsarsuaq"
    ],
    "name:dan_x_preferred":[
        "Narsarsuaq"
    ],
    "name:deu_x_preferred":[
        "Narsarsuaq"
    ],
    "name:eng_x_preferred":[
        "Narsarsuaq"
    ],
    "name:eus_x_preferred":[
        "Narsarsuaq"
    ],
    "name:fao_x_preferred":[
        "Narsarsuaq"
    ],
    "name:fra_x_preferred":[
        "Narsarsuaq"
    ],
    "name:isl_x_preferred":[
        "Narsarsuaq"
    ],
    "name:ita_x_preferred":[
        "Narsarsuaq"
    ],
    "name:jpn_x_preferred":[
        "\u30ca\u30eb\u30b5\u30eb\u30b9\u30a2\u30fc\u30af"
    ],
    "name:kal_x_preferred":[
        "Narsarsuaq"
    ],
    "name:kat_x_preferred":[
        "\u10dc\u10d0\u10e0\u10e1\u10d0\u10e0\u10e1\u10e3\u10d0\u10d9\u10d8"
    ],
    "name:kor_x_preferred":[
        "\ub098\ub974\uc0ac\uc218\uc544\ud06c"
    ],
    "name:lit_x_preferred":[
        "Narsarsuakas"
    ],
    "name:nld_x_preferred":[
        "Narsarsuaq"
    ],
    "name:nob_x_preferred":[
        "Narsarsuaq"
    ],
    "name:oci_x_preferred":[
        "Narsarsuaq"
    ],
    "name:pol_x_preferred":[
        "Narsarsuaq"
    ],
    "name:por_x_preferred":[
        "Narsarsuaq"
    ],
    "name:rus_x_preferred":[
        "\u041d\u0430\u0440\u0441\u0430\u0440\u0441\u0443\u0430\u043a"
    ],
    "name:spa_x_preferred":[
        "Narsarsuaq"
    ],
    "name:swe_x_preferred":[
        "Narsarsuaq"
    ],
    "name:ukr_x_preferred":[
        "\u041d\u0430\u0440\u0441\u0441\u0430\u0440\u0441\u0441\u0443\u0430\u043a"
    ],
    "name:und_x_variant":[
        "Narsarssuak"
    ],
    "name:zho_x_preferred":[
        "\u7d0d\u6c99\u65af\u74e6\u54e5"
    ],
    "qs_pg:aaroncc":"GL",
    "qs_pg:gn_country":"GL",
    "qs_pg:gn_fcode":"PPL",
    "qs_pg:gn_pop":154,
    "qs_pg:name":"Narssarssuaq",
    "qs_pg:name_adm0":"Gr\u00f8nland",
    "qs_pg:name_adm1":"Vestgronland",
    "qs_pg:photos":121,
    "qs_pg:photos_1k":25,
    "qs_pg:photos_9k":1,
    "qs_pg:photos_9r":3,
    "qs_pg:photos_all":121,
    "qs_pg:photos_sr":3,
    "qs_pg:pop_sr":1,
    "qs_pg:qs_pg_placetype":"locality",
    "qs_pg:qs_pg_placetype_gp":"Town",
    "qs_pg:woe_adm0":23424828,
    "woe:adm0_id":23424828,
    "woe:name_adm0":"Gr\u00f8nland",
    "woe:name_adm1":"Vestgronland",
    "woe:placetype":"Town",
    "wof:name":"Narssarssuaq",
    "wof:placetype":"locality",
    "wof:population":154
},
  "geometry": {"coordinates":[-45.41667,61.16667],"type":"Point"}
}