{
  "type": "Feature",
  "properties": {
    "gn:admin1_code":"06",
    "gn:asciiname":"Saqqarliit",
    "gn:country_code":"GL",
    "gn:dem":1,
    "gn:feature_class":"P",
    "gn:feature_code":"PPL",
    "gn:name":"Saqqarliit",
    "gn:population":0,
    "gn:timezone":"America/Godthab",
    "iso:country":"GL",
    "name:und_x_variant":[
        "Sarkardlit",
        "Sarqardl\u00eet",
        "Saqqarliit"
    ],
    "wof:name":"Saqqarliit",
    "wof:placetype":"locality"
},
  "geometry": {"coordinates":[-52.46666999999999,66.86667],"type":"Point"}
}