{
  "type": "Feature",
  "properties": {
    "gn:admin1_code":"07",
    "gn:asciiname":"Qeertartivatsiaq",
    "gn:country_code":"GL",
    "gn:dem":-9999,
    "gn:feature_class":"P",
    "gn:feature_code":"PPL",
    "gn:name":"Qeertartivatsiaq",
    "gn:population":0,
    "gn:timezone":"America/Godthab",
    "iso:country":"GL",
    "name:und_x_variant":[
        "Qeqertarssuatsiaq",
        "Qeertartivatsiaq"
    ],
    "wof:name":"Qeertartivatsiaq",
    "wof:placetype":"locality"
},
  "geometry": {"coordinates":[-38.01667,65.83333],"type":"Point"}
}