{
  "type": "Feature",
  "properties": {
    "gn:admin1_code":"05",
    "gn:asciiname":"Kittorsaq",
    "gn:country_code":"GL",
    "gn:dem":-9999,
    "gn:feature_class":"P",
    "gn:feature_code":"PPL",
    "gn:name":"Kittorsaq",
    "gn:population":0,
    "gn:timezone":"America/Godthab",
    "iso:country":"GL",
    "name:und_x_variant":[
        "Kigtorsaq",
        "Kitorsak",
        "Kigtorsak",
        "Kittorsaq"
    ],
    "wof:name":"Kittorsaq",
    "wof:placetype":"locality"
},
  "geometry": {"coordinates":[-56.73333,73.95],"type":"Point"}
}