{
  "type": "Feature",
  "properties": {
    "gn:admin1_code":"05",
    "gn:asciiname":"Appaarsuit",
    "gn:country_code":"GL",
    "gn:dem":17,
    "gn:feature_class":"P",
    "gn:feature_code":"PPL",
    "gn:name":"Appaarsuit",
    "gn:population":0,
    "gn:timezone":"America/Thule",
    "iso:country":"GL",
    "name:und_x_variant":[
        "Agparssuit",
        "Appaarsuit"
    ],
    "wof:name":"Appaarsuit",
    "wof:placetype":"locality"
},
  "geometry": {"coordinates":[-72.66667,77.41667],"type":"Point"}
}