{
  "type": "Feature",
  "properties": {
    "gn:gn_country":"GL",
    "gn:gn_fcode":"PPL",
    "gn:gn_pop":7,
    "gn:population":7,
    "iso:country":"GL",
    "qs_pg:aaroncc":"GL",
    "qs_pg:gn_country":"GL",
    "qs_pg:gn_fcode":"PPL",
    "qs_pg:gn_pop":7,
    "qs_pg:name":"Neriunaq",
    "qs_pg:photos_9r":0,
    "qs_pg:photos_sr":0,
    "qs_pg:pop_sr":1,
    "qs_pg:qs_pg_placetype":"locality",
    "wof:name":"Neriunaq",
    "wof:placetype":"locality",
    "wof:population":7
},
  "geometry": {"coordinates":[-50.31667,64.46666999999999],"type":"Point"}
}