{
  "type": "Feature",
  "properties": {
    "gn:country":"GL",
    "gn:fcode":"ADM3",
    "gn:population":3068,
    "iso:country":"GL",
    "name:dan_x_preferred":[
        "Ammassalik Kommune"
    ],
    "name:und_x_variant":[
        "Tasiilap Kommunia"
    ],
    "qs_pg:aaroncc":"GL",
    "qs_pg:gn_country":"GL",
    "qs_pg:gn_fcode":"ADM3",
    "qs_pg:gn_pop":3068,
    "qs_pg:name":"Ammassallip Kommunia",
    "qs_pg:photos_9r":0,
    "qs_pg:photos_sr":0,
    "qs_pg:pop_sr":4,
    "qs_pg:qs_pg_placetype":"localadmin",
    "wof:name":"Ammassallip Kommunia",
    "wof:placetype":"localadmin",
    "wof:population":3068
},
  "geometry": {"coordinates":[-37.66667,65.63333],"type":"Point"}
}