{
  "type": "Feature",
  "properties": {
    "gn:admin1_code":"05",
    "gn:asciiname":"Tartunaq",
    "gn:country_code":"GL",
    "gn:dem":-9999,
    "gn:feature_class":"P",
    "gn:feature_code":"PPL",
    "gn:name":"Tartunaq",
    "gn:population":0,
    "gn:timezone":"America/Godthab",
    "iso:country":"GL",
    "name:und_x_variant":[
        "Tartanaq",
        "Tartunak",
        "Tartunaq"
    ],
    "wof:name":"Tartunaq",
    "wof:placetype":"locality"
},
  "geometry": {"coordinates":[-52.21667,70.03333000000001],"type":"Point"}
}