{
  "type": "Feature",
  "properties": {
    "gn:gn_country":"GL",
    "gn:gn_fcode":"PPL",
    "gn:gn_pop":9,
    "gn:population":9,
    "iso:country":"GL",
    "name:cze_x_preferred":[
        "Itterajivit"
    ],
    "name:dan_x_preferred":[
        "Kap Hope"
    ],
    "name:dut_x_preferred":[
        "Itterajivit"
    ],
    "name:eng_x_preferred":[
        "Itterajivit"
    ],
    "name:fre_x_preferred":[
        "Itterajivit"
    ],
    "name:ita_x_preferred":[
        "Itterajivit"
    ],
    "name:kal_x_preferred":[
        "Ittaajimmiut"
    ],
    "name:nob_x_preferred":[
        "Itterajivit"
    ],
    "name:por_x_preferred":[
        "Itterajivit"
    ],
    "name:spa_x_preferred":[
        "Itterajivit"
    ],
    "name:unk_x_variant":[
        "Itterajivit"
    ],
    "qs_pg:aaroncc":"GL",
    "qs_pg:gn_country":"GL",
    "qs_pg:gn_fcode":"PPL",
    "qs_pg:gn_pop":9,
    "qs_pg:name":"Kap Hope",
    "qs_pg:photos_9r":0,
    "qs_pg:photos_sr":0,
    "qs_pg:pop_sr":1,
    "qs_pg:qs_pg_placetype":"locality",
    "wof:name":"Kap Hope",
    "wof:placetype":"locality",
    "wof:population":9
},
  "geometry": {"coordinates":[-22.32975,70.4588],"type":"Point"}
}