{
  "type": "Feature",
  "properties": {
    "gn:admin1_code":"05",
    "gn:asciiname":"Upernavissuaq",
    "gn:country_code":"GL",
    "gn:dem":268,
    "gn:feature_class":"P",
    "gn:feature_code":"PPL",
    "gn:name":"Upernavissuaq",
    "gn:population":0,
    "gn:timezone":"America/Thule",
    "iso:country":"GL",
    "name:und_x_variant":[
        "Upernavigssuak",
        "Upernavissuaq"
    ],
    "wof:name":"Upernavissuaq",
    "wof:placetype":"locality"
},
  "geometry": {"coordinates":[-71.83333,77.31667],"type":"Point"}
}