{
  "type": "Feature",
  "properties": {
    "gn:population":1633,
    "iso:country":"GL",
    "name:ara_x_preferred":[
        "\u0646\u0627\u0631\u0633\u0627\u0643"
    ],
    "name:ast_x_preferred":[
        "Narsaq"
    ],
    "name:bel_x_variant":[
        "\u041d\u0430\u0440\u0441\u0430\u043a"
    ],
    "name:cat_x_preferred":[
        "Narsaq"
    ],
    "name:ceb_x_preferred":[
        "Narsaq"
    ],
    "name:ces_x_preferred":[
        "Narsaq"
    ],
    "name:dan_x_preferred":[
        "Narsaq"
    ],
    "name:deu_x_preferred":[
        "Narsaq"
    ],
    "name:ell_x_preferred":[
        "\u039d\u03ac\u03c1\u03c3\u03b1\u03ba"
    ],
    "name:eng_x_preferred":[
        "Narsaq"
    ],
    "name:fin_x_preferred":[
        "Narsaq"
    ],
    "name:fra_x_preferred":[
        "Narsaq"
    ],
    "name:frr_x_preferred":[
        "Narsaq"
    ],
    "name:heb_x_preferred":[
        "\u05e0\u05d0\u05e8\u05e1\u05d0\u05e7"
    ],
    "name:hun_x_preferred":[
        "Narsaq"
    ],
    "name:isl_x_preferred":[
        "Narsaq"
    ],
    "name:ita_x_preferred":[
        "Narsaq"
    ],
    "name:jpn_x_preferred":[
        "\u30ca\u30eb\u30b5\u30fc\u30af"
    ],
    "name:kal_x_preferred":[
        "Narsaq"
    ],
    "name:kat_x_preferred":[
        "\u10dc\u10d0\u10e0\u10e1\u10d0\u10d9\u10d8"
    ],
    "name:mkd_x_preferred":[
        "\u041d\u0430\u0440\u0441\u0430\u043a"
    ],
    "name:nld_x_preferred":[
        "Narsaq"
    ],
    "name:nob_x_preferred":[
        "Narsaq"
    ],
    "name:nor_x_preferred":[
        "Narsaq"
    ],
    "name:pol_x_preferred":[
        "Narsaq"
    ],
    "name:por_x_preferred":[
        "Narsaq"
    ],
    "name:rus_x_preferred":[
        "\u041d\u0430\u0440\u0441\u0430\u043a"
    ],
    "name:sgs_x_preferred":[
        "Narsaks"
    ],
    "name:spa_x_preferred":[
        "Narsaq"
    ],
    "name:swe_x_preferred":[
        "Narsaq"
    ],
    "name:ukr_x_preferred":[
        "\u041d\u0430\u0440\u0441\u0430\u043a"
    ],
    "name:und_x_variant":[
        "Narsak"
    ],
    "name:zho_x_preferred":[
        "\u7eb3\u8428\u514b"
    ],
    "qs:a0":"Kalaallit Nunaat#Gr\u00f8nland",
    "qs:a1":"*Kommune Kujalleq",
    "qs:a1r":"0",
    "qs:adm0":"Kalaallit Nunaat#Gr\u00f8nland",
    "qs:la_lc":"*",
    "qs:level":"locality",
    "qs:loc":"Narsaq",
    "qs:loc_alt":"Narsaq",
    "qs:pop":0,
    "qs:type":"buffered point",
    "wd:population":1492,
    "wd:wordcount":1154,
    "wof:name":"Narsaq",
    "wof:placetype":"locality",
    "wof:population":1492
},
  "geometry": {"coordinates":[-46.048855,60.954487],"type":"Point"}
}