{
  "type": "Feature",
  "properties": {
    "iso:country":"GL",
    "qs_pg:aaroncc":"GL",
    "qs_pg:name":"Constable Pynt",
    "qs_pg:name_adm0":"Gr\u00f8nland",
    "qs_pg:name_adm1":"Ostgronland",
    "qs_pg:photos":33,
    "qs_pg:photos_1k":7,
    "qs_pg:photos_9k":1,
    "qs_pg:photos_9r":2,
    "qs_pg:photos_all":33,
    "qs_pg:photos_sr":2,
    "qs_pg:pop_sr":0,
    "qs_pg:qs_pg_placetype":"locality",
    "qs_pg:qs_pg_placetype_gp":"Town",
    "qs_pg:woe_adm0":23424828,
    "woe:adm0_id":23424828,
    "woe:name_adm0":"Gr\u00f8nland",
    "woe:name_adm1":"Ostgronland",
    "woe:placetype":"Town",
    "wof:name":"Constable Pynt",
    "wof:placetype":"locality"
},
  "geometry": {"coordinates":[-22.646856,70.74276999999999],"type":"Point"}
}