{
  "type": "Feature",
  "properties": {
    "gn:admin1_code":"05",
    "gn:asciiname":"Manermiut",
    "gn:country_code":"GL",
    "gn:dem":1,
    "gn:feature_class":"P",
    "gn:feature_code":"PPL",
    "gn:name":"Manermiut",
    "gn:population":0,
    "gn:timezone":"America/Godthab",
    "iso:country":"GL",
    "wof:name":"Manermiut",
    "wof:placetype":"locality"
},
  "geometry": {"coordinates":[-53.13333000000001,68.59999999999999],"type":"Point"}
}